rmsutil/__init__.py
rmsutil/crypto.py
rmsutil/system.py
rmsutil-1.1.dist-info/DESCRIPTION.rst
rmsutil-1.1.dist-info/METADATA
rmsutil-1.1.dist-info/metadata.json
rmsutil-1.1.dist-info/RECORD
rmsutil-1.1.dist-info/top_level.txt
rmsutil-1.1.dist-info/WHEEL
tests/__init__.py
tests/crypto/__init__.py
tests/crypto/test_opaque_id.py
tests/system/__init__.py
tests/system/test_override_argv.py
tests/system/test_update_env.py
