Metadata-Version: 2.0
Name: rmsutil
Version: 1.1
Summary: Common utilities used in RMS projects
Home-page: UNKNOWN
Author: Rackspace
Author-email: UNKNOWN
License: Apache 2.0
Platform: UNKNOWN
Requires-Dist: six
